{"name":"sp_market2","display_name":"SP Market 2","version":"4.2.7","author":{"name":"MagenTech","email":"contact@magentech.com","url":"http:\/\/www.magentech.com"},"meta":{"compatibility":{"from":"1.7.0.0","to":null},"available_layouts":{"layout-full-width":{"name":"Full Width","description":"No side columns, ideal for distraction-free pages such as product pages."},"layout-both-columns":{"name":"Three Columns","description":"One large central column and 2 side columns."},"layout-left-column":{"name":"Two Columns, small left column","description":"Two columns with a small left column"},"layout-right-column":{"name":"Two Columns, small right column","description":"Two columns with a small right column"}}},"assets":null,"global_settings":{"configuration":{"PS_IMAGE_QUALITY":"png"},"modules":{"to_enable":["smartblog","smartbloghomelatestnews","spbanner","spblockcart","spblockcurrency","spblocklanguage","spblocknewsletter","spblockuserinfo","spcategories","spcustomhtml","spfilterproducts","spfooterlinks","sphomeslider","splistingtabs","spmegamenu","spsearchpro","spthemeconfigurator","spverticalmenu","spstepcheckout","spproductcomments","contactform","spmanufactureslider"],"to_disable":["ps_shoppingcart","ps_linklist","ps_customeraccountlinks","ps_contactinfo","blockreassurance","ps_categorytree","cronjobs","ps_imageslider","ps_customtext","ps_searchbar"]},"hooks":{"modules_to_hook":{"displayBackOfficeHeader":["spfilterproducts"],"displayProductButtons":["ps_sharebuttons"],"displayLeftColumn":["ps_facetedsearch",{"spcustomhtml":{"except_pages":["category"]}},"spfilterproducts"],"displayFilterproducts1":["spfilterproducts"],"displayFilterproducts2":["spfilterproducts"],"displayFilterproducts3":["spfilterproducts"],"displayFilterproducts4":["spfilterproducts"],"displayFilterproducts5":["spfilterproducts"],"displayFilterproducts6":["spfilterproducts"],"displayFilterproducts7":["spfilterproducts"],"displayProductCountDown":["spfilterproducts"],"displayFooterMiddle":["spcustomhtml"],"displayCustomhtmlMobile1":["spcustomhtml"],"displayCustomhtmlMobile2":["spcustomhtml"],"displayCustomhtml1":["spcustomhtml"],"displayCustomhtml2":["spcustomhtml"],"displayCustomhtml3":["spcustomhtml"],"displayCustomhtml4":["spcustomhtml"],"displayCustomhtml5":["spcustomhtml"],"displayCustomhtml6":["spcustomhtml"],"displayCustomhtml7":["spcustomhtml"],"displayCustomhtml8":["spcustomhtml"],"displayCustomhtml9":["spcustomhtml"],"displayCustomhtml10":["spcustomhtml"],"displayCustomhtml11":["spcustomhtml"],"displayCustomhtml12":["spcustomhtml"],"displayCustomhtml13":["spcustomhtml"],"displayCustomhtml14":["spcustomhtml"],"displayCustomhtml15":["spcustomhtml"],"displayCustomhtml16":["spcustomhtml"],"displayCustomhtml17":["spcustomhtml"],"displayCustomhtml18":["spcustomhtml"],"displayCustomhtml19":["spcustomhtml"],"displayCustomhtml20":["spcustomhtml"],"displayCustomhtml21":["spcustomhtml"],"displayCustomhtml22":["spcustomhtml"],"displayCustomhtml23":["spcustomhtml"],"displayCustomhtml24":["spcustomhtml"],"displayCustomhtml25":["spcustomhtml"],"displayCustomhtml26":["spcustomhtml"],"displayCustomhtml27":["spcustomhtml"],"displayCustomhtml28":["spcustomhtml"],"displayCustomhtml29":["spcustomhtml"],"displayCustomhtml30":["spcustomhtml"]}},"image_types":{"cart_default":{"width":90,"height":90,"scope":["products"]},"small_default":{"width":130,"height":130,"scope":["products","categories","manufacturers","suppliers"]},"medium_default":{"width":452,"height":452,"scope":["products","manufacturers","suppliers"]},"home_default":{"width":270,"height":270,"scope":["products"]},"large_default":{"width":800,"height":800,"scope":["products","manufacturers","suppliers"]},"category_default":{"width":141,"height":180,"scope":["categories"]},"stores_default":{"width":170,"height":115,"scope":["stores"]},"category_home4":{"width":190,"height":270,"scope":["products"]},"category_icon":{"width":40,"height":40,"scope":["categories"]},"deal_home_default":{"width":350,"height":350,"scope":["products"]},"deal_home3_default":{"width":430,"height":430,"scope":["products"]}}},"theme_settings":{"default_layout":"layout-full-width","layouts":{"category":"layout-left-column","best-sales":"layout-left-column","new-products":"layout-left-column","prices-drop":"layout-left-column","contact":"layout-left-column","product":"layout-left-column"}},"dependencies":{"modules":["smartblog","smartbloghomelatestnews","spbanner","spblockcart","spblockcurrency","spblocklanguage","spblocknewsletter","spblockuserinfo","spcategories","spcustomhtml","spfilterproducts","spfooterlinks","sphomeslider","splistingtabs","spmegamenu","spsearchpro","spthemeconfigurator","spverticalmenu","spstepcheckout","spproductcomments","contactform","spmanufactureslider"]}}